fabricatio_team/__init__.py
fabricatio_team/config.py
fabricatio_team/py.typed
fabricatio_team/actions/__init__.py
fabricatio_team/capabilities/__init__.py
fabricatio_team/capabilities/digest.py
fabricatio_team/capabilities/team.py
fabricatio_team/models/__init__.py
fabricatio_team/models/team.py
fabricatio_team/workflows/__init__.py
tests/test_team.py
fabricatio_team-0.2.1.dist-info/METADATA
fabricatio_team-0.2.1.dist-info/WHEEL
fabricatio_team-0.2.1.dist-info/RECORD
